setup.cfg
setup.py
pyseidon/__init__.py
pyseidon.egg-info/PKG-INFO
pyseidon.egg-info/SOURCES.txt
pyseidon.egg-info/dependency_links.txt
pyseidon.egg-info/top_level.txt
pyseidon/client/Makefile
pyseidon/client/__init__.py
pyseidon/client/lru_cache.py
pyseidon/client/pyseidon
pyseidon/client/pyseidon-client
pyseidon/client/pyseidon.c
pyseidon/handlers/__init__.py