Metadata-Version: 1.1
Name: pyseidon
Version: 0.1.0
Summary: A boot-once, run-many-times framework for Python
Home-page: https://github.com/gdb/pyseidon
Author: Greg Brockman
Author-email: gdb@gregbrockman.com
License: MIT
Keywords: pyseidon
Platform: UNKNOWN
Classifier: Development Status :: 3 - Alpha
Classifier: Intended Audience :: Developers
Classifier: License :: OSI Approved :: MIT License
Classifier: Programming Language :: Python :: 2.7
